AUTHORS
COPYRIGHT
ChangeLog
MANIFEST.in
README.md
setup.py
docs/Makefile
docs/_static
docs/conf.py
docs/index.rst
docs/install.rst
docs/overview.rst
docs/usage.rst
docs/man/snf-image-creator.rst
docs/man/snf-mkimage.rst
docs/snapshots/confirm.png
docs/snapshots/custom-vm.png
docs/snapshots/image-creator.png
docs/snapshots/main_menu.png
docs/snapshots/mkimage-fin.png
docs/snapshots/mkimage-results.png
docs/snapshots/mkimage-wizard.png
docs/snapshots/mkimage1.png
docs/snapshots/mkimage2.png
docs/snapshots/mkimage3.png
docs/snapshots/mkimage4.png
docs/snapshots/qemu-live.png
docs/snapshots/qemu-partition.png
docs/snapshots/select_media.png
docs/snapshots/wizard.png
image_creator/__init__.py
image_creator/bootloader.py
image_creator/bundle_volume.py
image_creator/dialog_main.py
image_creator/dialog_menu.py
image_creator/dialog_util.py
image_creator/dialog_wizard.py
image_creator/disk.py
image_creator/gpt.py
image_creator/image.py
image_creator/kamaki_wrapper.py
image_creator/main.py
image_creator/rsync.py
image_creator/util.py
image_creator/version.py
image_creator/help/__init__.py
image_creator/help/configuration_tasks.rst
image_creator/help/image_properties.rst
image_creator/os_type/__init__.py
image_creator/os_type/archlinux.py
image_creator/os_type/bsd.py
image_creator/os_type/freebsd.py
image_creator/os_type/hurd.py
image_creator/os_type/linux.py
image_creator/os_type/netbsd.py
image_creator/os_type/openbsd.py
image_creator/os_type/rhel.py
image_creator/os_type/slackware.py
image_creator/os_type/ubuntu.py
image_creator/os_type/unix.py
image_creator/os_type/unknown.py
image_creator/os_type/unsupported.py
image_creator/os_type/windows/__init__.py
image_creator/os_type/windows/powershell.py
image_creator/os_type/windows/registry.py
image_creator/os_type/windows/vm.py
image_creator/os_type/windows/winexe.py
image_creator/output/__init__.py
image_creator/output/cli.py
image_creator/output/composite.py
image_creator/output/dialog.py
image_creator/output/syslog.py
snf_image_creator.egg-info/PKG-INFO
snf_image_creator.egg-info/SOURCES.txt
snf_image_creator.egg-info/dependency_links.txt
snf_image_creator.egg-info/entry_points.txt
snf_image_creator.egg-info/requires.txt
snf_image_creator.egg-info/top_level.txt