Metadata-Version: 1.1
Name: snf-image-creator
Version: 0.10
Summary: Command line tool for creating images
Home-page: https://github.com/grnet/snf-image
Author: Synnefo development team
Author-email: synnefo-devel@googlegroups.com
License: GNU GPLv3
Download-URL: https://pypi.python.org/pypi/snf_image_creator
Keywords: cloud IaaS OS images
Platform: UNKNOWN
Classifier: Development Status :: 5 - Production/Stable
Classifier: Environment :: Console
Classifier: Environment :: Console :: Curses
Classifier: Intended Audience :: Developers
Classifier: Intended Audience :: System Administrators
Classifier: License :: OSI Approved :: GNU General Public License v3 (GPLv3)
Classifier: Operating System :: POSIX :: Linux
Classifier: Programming Language :: Python :: 2.6
Classifier: Programming Language :: Python :: 2.7
